MANIFEST.in
README.md
cirrus.conf
requirements.txt
setup.py
test-requirements.txt
./sgrid/__init__.py
./sgrid/grid.py
./sgrid/node.py
./sgrid/util.py
sgrid/docker-compose.yml
sgrid.egg-info/PKG-INFO
sgrid.egg-info/SOURCES.txt
sgrid.egg-info/dependency_links.txt
sgrid.egg-info/requires.txt
sgrid.egg-info/top_level.txt