Metadata-Version: 1.1
Name: sgrid
Version: 0.0.4
Summary: Python class & context manager for starting a headless Seleneium Grid.
Home-page: https://github.com/limx0/sgrid
Author: limx0
Author-email: bradley.mcelroy@live.com
License: UNKNOWN
Platform: UNKNOWN
Provides: sgrid
